mlcvzoo_util/__init__.py
mlcvzoo_util/image_io_utils.py
mlcvzoo_util/mlcvzoo_cli_tool.py
mlcvzoo_util/py.typed
mlcvzoo_util/cvat_annotation_handler/__init__.py
mlcvzoo_util/cvat_annotation_handler/configuration.py
mlcvzoo_util/cvat_annotation_handler/cvat_annotation_handler.py
mlcvzoo_util/cvat_annotation_handler/cvat_dumper.py
mlcvzoo_util/cvat_annotation_handler/cvat_uploader.py
mlcvzoo_util/cvat_annotation_handler/utils.py
mlcvzoo_util/logger/__init__.py
mlcvzoo_util/logger/logger.py
mlcvzoo_util/ls_tracking_task_converter/__init__.py
mlcvzoo_util/ls_tracking_task_converter/ls_tracking_task_converter.py
mlcvzoo_util/model_evaluator/__init__.py
mlcvzoo_util/model_evaluator/configuration.py
mlcvzoo_util/model_evaluator/metric_factory.py
mlcvzoo_util/model_evaluator/model_evaluator.py
mlcvzoo_util/model_evaluator/structs.py
mlcvzoo_util/model_timer/__init__.py
mlcvzoo_util/model_timer/configuration.py
mlcvzoo_util/model_timer/model_timer.py
mlcvzoo_util/model_trainer/__init__.py
mlcvzoo_util/model_trainer/configuration.py
mlcvzoo_util/model_trainer/model_trainer.py
mlcvzoo_util/pre_annotation_tool/__init__.py
mlcvzoo_util/pre_annotation_tool/configuration.py
mlcvzoo_util/pre_annotation_tool/pre_annotation_tool.py
mlcvzoo_util/video_image_creator/__init__.py
mlcvzoo_util/video_image_creator/configuration.py
mlcvzoo_util/video_image_creator/video_image_creator.py
mlcvzoo_util-1.0.0.dist-info/LICENSE
mlcvzoo_util-1.0.0.dist-info/METADATA
mlcvzoo_util-1.0.0.dist-info/WHEEL
mlcvzoo_util-1.0.0.dist-info/entry_points.txt
mlcvzoo_util-1.0.0.dist-info/top_level.txt
mlcvzoo_util-1.0.0.dist-info/RECORD
